polkadot_gateway/__init__.py
polkadot_gateway/exceptions.py
polkadot_gateway/polkadot.py
polkadot_gateway/utils.py
polkadot_gateway-0.1.2.dist-info/LICENSE
polkadot_gateway-0.1.2.dist-info/METADATA
polkadot_gateway-0.1.2.dist-info/WHEEL
polkadot_gateway-0.1.2.dist-info/top_level.txt
polkadot_gateway-0.1.2.dist-info/RECORD
