Metadata-Version: 2.1
Name: polkadot-gateway
Version: 0.1.2
Summary: Abstractions for the Polkadot ecosystem
Author-email: Karim Jedda <karim@parity.io>
License: GNU GENERAL PUBLIC LICENSE
Project-URL: Homepage, https://github.com/KarimJedda/polkadot-gateway
Keywords: polkadot,blockchain,cryptocurrency
Classifier: License :: OSI Approved :: MIT License
Classifier: Programming Language :: Python
Classifier: Programming Language :: Python :: 3
Requires-Python: >=3.7
License-File: LICENSE
Requires-Dist: substrate-interface==1.7.10
Provides-Extra: dev
Requires-Dist: pytest==8.3.2; extra == "dev"
Requires-Dist: ruff==0.6.2; extra == "dev"
Requires-Dist: twine==5.1.1; extra == "dev"
Requires-Dist: build==1.2.1; extra == "dev"
